{
  "attributes": [
    {
      "name": "lastGoodPrice",
      "type": "uint256",
      "contract_function": "lastGoodPrice",
      "parameters": []
    },
    {
      "name": "price",
      "type": "uint256",
      "contract_function": "price",
      "parameters": []
    },
    {
      "name": "fetchPrice",
      "type": "uint256",
      "contract_function": "fetchPrice",
      "parameters": []
    }
  ],
  "typescript_interfaces": {
    "contract_snapshot_interface_code": "interface MockPriceOracleSnapshot {\n  lastGoodPrice: bigint;\n  price: bigint;\n  fetchPrice: bigint;\n}\n",
    "interface_name": "MockPriceOracleSnapshot"
  }
}